Metadata-Version: 2.1
Name: odoo10-addon-sale-procurement-amendment
Version: 10.0.1.0.1
Summary: Allow to reflect confirmed sale lines quantity amendments to procurements
Home-page: https://github.com/OCA/sale-workflow
Author: ACSONE SA/NV,Odoo Community Association (OCA)
Author-email: support@odoo-community.org
License: AGPL-3
Platform: UNKNOWN
Classifier: Programming Language :: Python
Classifier: Framework :: Odoo
Classifier: License :: OSI Approved :: GNU Affero General Public License v3
Classifier: Development Status :: 4 - Beta
Requires-Python: ~=2.7
Requires-Dist: odoo (<10.1dev,>=10.0)
